{
    "News": [
        {
            "Number": "100047",
            "Title": "★('ω')★",
            "Subtitle": "<color=#00c1ff>直ったよ！",
            "Short": "<color=#00c1ff>開発版ではアナウンスあったの！",
            "Body": "★この問題は解決してます。\n\nなにかしら問題あったりアナウンスがあった場合ここでもしますが。\nDiscordでお知らせするのが速いと思います！入っといてね！",
            "Date": "2025-02-02T00:00:00Z"
        },
        {
            "Number": "100051",
            "Title": "ちょっとややこしくなっちゃった！",
            "Subtitle": "<color=#00c1ff>Town Of Host-K v.51.10.27.12</color>",
            "Short": "<color=#00c1ff>◆TOH-K v51.10.27.12</color>",
            "Body": "<size=80%>かくかくしかじかでネ...\n<size=100%>！このバージョンは自動アップデートを使用できません！\n<nobr><link=\"https://github.com/KYMario/TownOfHost-K/wiki/導入方法・アップデート方法#手動アップデートの場合\">Wiki</nobr></link>に手動アップデートの方法を記載しております。\n手動で.dllを入れ替えてください。\n\nまたは、ニュースを閉じたらある、バージョン切り替えボタンから、「51.10.27.12」に切り替えてください。\n\n</size>\n<size=125%>【バグ修正】</size>\n・シェフ、アーソニスト等の役職がインポスターを切れない問題の修正\n会議後、名前変更が正常に行われない問題の修正\n\n<size=125%>【仕様変更】</size>\n・そこそこ！\n・また、本家TOH5.1.10に対応",
            "Date": "2025-03-16T04:15:00Z"
        },
        {
            "Number": "100052",
            "Title": "(Kが)だめなのよ～",
            "Subtitle": "<color=#00c1ff>Town Of Host-K v.51.10.28</color>",
            "Short": "<color=#00c1ff>◆TOH-K v.51.10.28</color>",
            "Body": "<size=80%>やぁ！もう3月が終わるんだ！...は!?\n\nAmongUs本体最新版に対応してます。過去バージョンは対応してません。\n\n<size=125%>【バグ修正】</size>\n・一定条件下の時、スポーン時バグる問題の修正\n・マドンナラバーのタスクが勝利カウントに入る問題の修正\n・8~9人以上で落ちる奴の対策設定がONの時、イントロ暗転する問題の対応\n\n<size=125%>【仕様変更】</size>\n・通信を軽くしようとしてるんです。\n\n・AmongUs v16.0.0 に対応最後のsって多分steamのsだよね。(どうでもいい)アプデ対応中、りぃりぃにAmongUs公式から本日公開されたコラボの動画ループ再生されてました。\n頭狂う。\nby.Panda",
            "Date": "2025-03-26T05:40:00Z"
        }
    ]
}